htm_pyx/__init__.py
htm_pyx/cli.py
htm_pyx/register.py
htm_pyx/transpile.py
htm_pyx/utils.py
htm_pyx-0.1.0.dev0.dist-info/LICENSE
htm_pyx-0.1.0.dev0.dist-info/METADATA
htm_pyx-0.1.0.dev0.dist-info/WHEEL
htm_pyx-0.1.0.dev0.dist-info/entry_points.txt
htm_pyx-0.1.0.dev0.dist-info/top_level.txt
htm_pyx-0.1.0.dev0.dist-info/RECORD
