Metadata-Version: 2.1
Name: htm-pyx
Version: 0.1.0.dev0
Summary: Control the web with Python
Home-page: https://github.com/rmorshea/htm-pyx
Author: Ryan Morshead
Author-email: ryan.morshead@gmail.com
License: MIT
Keywords: JSX
Platform: Linux
Platform: Mac OS X
Platform: Windows
Requires-Python: >=3.6,<4.0
Requires-Dist: docopt (==0.6.2)
Requires-Dist: mypy-extensions (==0.4.1)
